{
  "version": "1.0.0",
  "projectName": "Lumisky",
  "projectRoot": "d:/Lumisky",
  "analyzedAt": "2026-05-23T17:05:52Z",
  "gitCommitHash": "3733ea8cdf69c74bb49a5de258165f942f76cebe",
  "stats": {
    "totalNodes": 525,
    "totalEdges": 856,
    "totalLayers": 9,
    "tourSteps": 12,
    "sourceFiles": 116,
    "configFiles": 46,
    "docFiles": 43
  },
  "phases": {
    "scan": "completed",
    "analyze": "completed",
    "assembleReview": "completed",
    "architecture": "completed",
    "tour": "completed",
    "review": "completed",
    "fingerprints": "completed"
  }
}
